{
    "tags": {
        "allowUnknownTags": true,
        "dictionaries": ["jsdoc", "closure"]
    },
    "source": {
        "include": ["package.json", "README.md"],
        "exclude": ["node_modules", "docs", "tests", "mocks"]
    },
    "plugins": [
        "plugins/markdown",
        "plugins/summarize"
    ],
    "recurseDepth": 2,
    "templates": {
        "cleverLinks": false,
        "monospaceLinks": false,
        "default": {
            "outputSourceFiles": false
        }
    },
    "opts": {
        "encoding": "utf8",
        "private": false,
        "template": "node_modules/clean-jsdoc-theme",
        "theme_opts": {
            "title": "IntAssi",
            "theme": "light",
            "filter": true,
            "create_style": "nav h2 .text { font-size:17px; } body::-webkit-scrollbar-track, .sidebar-list-div::-webkit-scrollbar-track { -webkit-box-shadow: inset 0 0 6px rgba(0, 0, 0, 0.3); background-color: #F5F5F5; } body::-webkit-scrollbar, .sidebar-list-div::-webkit-scrollbar { width: 10px; background-color: #F5F5F5; } body::-webkit-scrollbar-thumb, .sidebar-list-div::-webkit-scrollbar-thumb { background-color: #F90;  background-image: -webkit-linear-gradient(45deg, rgba(255, 255, 255, .2) 25%, transparent 25%, transparent 50%, rgba(255, 255, 255, .2) 50%, rgba(255, 255, 255, .2) 75%, transparent 75%, transparent) }"
        }
    }
}